{
  "categories": [
    {
      "id": "destination",
      "name": "目的地专题",
      "icon": "🌍",
      "description": "深度探索全球热门目的地"
    },
    {
      "id": "seasonal",
      "name": "季节特辑",
      "icon": "🍂",
      "description": "四季旅行灵感指南"
    },
    {
      "id": "food",
      "name": "美食专题",
      "icon": "🍜",
      "description": "舌尖上的环球旅行"
    },
    {
      "id": "accommodation",
      "name": "住宿指南",
      "icon": "🏨",
      "description": "特色酒店与民宿推荐"
    },
    {
      "id": "guide",
      "name": "攻略合集",
      "icon": "📝",
      "description": "实用旅行技巧与经验"
    }
  ],
  "magazines": [
    {
      "id": "sakura-2024",
      "title": "日本樱花季特辑",
      "subtitle": "春日追樱指南",
      "cover": "https://images.unsplash.com/photo-1522383225653-ed111181a951?w=600&h=800&fit=crop",
      "category": "seasonal",
      "publishDate": "2024-03-15",
      "author": "游导编辑部",
      "pages": 32,
      "views": 45678,
      "likes": 3245,
      "featured": true,
      "description": "收录东京、京都、大阪等地最佳赏樱地点，包含2024年樱花预测时间表和拍照攻略。"
    },
    {
      "id": "korea-food",
      "title": "韩国美食指南",
      "subtitle": "舌尖上的首尔",
      "cover": "https://images.unsplash.com/photo-1504674900247-0877df9cc836?w=600&h=800&fit=crop",
      "category": "food",
      "publishDate": "2024-02-20",
      "author": "美食探索家",
      "pages": 28,
      "views": 38921,
      "likes": 2890,
      "featured": true,
      "description": "深入探访首尔街头美食，从米其林餐厅到路边摊，开启一场味蕾之旅。"
    },
    {
      "id": "thailand-beach",
      "title": "泰国海岛度假",
      "subtitle": "碧海蓝天东南亚",
      "cover": "https://images.unsplash.com/photo-1504214208698-ea1916a2195a?w=600&h=800&fit=crop",
      "category": "destination",
      "publishDate": "2024-01-10",
      "author": "海岛旅行家",
      "pages": 36,
      "views": 52340,
      "likes": 4120,
      "featured": false,
      "description": "普吉岛、苏梅岛、甲米等多个人气海岛详细攻略，包含跳岛游路线推荐。"
    },
    {
      "id": "singapore-city",
      "title": "新加坡城市探索",
      "subtitle": "花园城市的魅力",
      "cover": "https://images.unsplash.com/photo-1525625293386-3f8f99389edd?w=600&h=800&fit=crop",
      "category": "destination",
      "publishDate": "2023-12-05",
      "author": "城市漫游者",
      "pages": 30,
      "views": 41230,
      "likes": 3560,
      "featured": false,
      "description": "从鱼尾狮到滨海湾，全方位探索这座融合多元文化的花园城市。"
    },
    {
      "id": "japan-winter",
      "title": "日本冬季温泉之旅",
      "subtitle": "雪景与温泉的邂逅",
      "cover": "https://images.unsplash.com/photo-1545569341-9eb8b30979d9?w=600&h=800&fit=crop",
      "category": "seasonal",
      "publishDate": "2023-11-20",
      "author": "温泉爱好者",
      "pages": 34,
      "views": 38920,
      "likes": 3100,
      "featured": false,
      "description": "北海道、九州等地的绝景温泉推荐，感受冰火两重天的极致体验。"
    },
    {
      "id": "europe-railway",
      "title": "欧洲铁路漫游",
      "subtitle": "坐着火车游欧洲",
      "cover": "https://images.unsplash.com/photo-1549880338-65ddcdfd017b?w=600&h=800&fit=crop",
      "category": "guide",
      "publishDate": "2023-10-15",
      "author": "铁路旅行家",
      "pages": 40,
      "views": 35670,
      "likes": 2890,
      "featured": false,
      "description": "Eurail通票完全指南，搭配多条经典铁路线路推荐，开启欧洲慢旅行。"
    },
    {
      "id": "bali-luxury",
      "title": "巴厘岛奢华度假",
      "subtitle": "明星同款海岛体验",
      "cover": "https://images.unsplash.com/photo-1537996194471-e657df975ab4?w=600&h=800&fit=crop",
      "category": "accommodation",
      "publishDate": "2023-09-25",
      "author": "奢华旅行家",
      "pages": 26,
      "views": 29840,
      "likes": 2450,
      "featured": false,
      "description": "乌布Villa、水明漾海滩club、最美悬崖酒店，巴厘岛顶级住宿全攻略。"
    },
    {
      "id": "vietnam-food",
      "title": "越南美食探秘",
      "subtitle": "河内到西贡的味觉之旅",
      "cover": "https://images.unsplash.com/photo-1503764654157-72d979d9af2f?w=600&h=800&fit=crop",
      "category": "food",
      "publishDate": "2023-08-18",
      "author": "东南亚美食家",
      "pages": 32,
      "views": 31450,
      "likes": 2680,
      "featured": false,
      "description": "从越南河粉到越南咖啡，探索越南街头美食的灵魂与独特风味。"
    }
  ],
  "subscriptions": [
    {
      "id": "monthly",
      "name": "月度订阅",
      "price": 29,
      "period": "month",
      "features": [
        "每月接收1期电子杂志",
        "解锁往期全部杂志",
        "参与杂志社活动",
        "专属会员社群"
      ],
      "popular": false
    },
    {
      "id": "yearly",
      "name": "年度订阅",
      "price": 259,
      "period": "year",
      "features": [
        "每月接收1期电子杂志",
        "解锁往期全部杂志",
        "参与杂志社活动",
        "专属会员社群",
        "获赠实体杂志1本",
        "优先参与线下活动"
      ],
      "popular": true
    }
  ],
  "contributionGuide": {
    "types": [
      {
        "type": "目的地攻略",
        "description": "分享你去过的目的地旅行经验和实用贴士"
      },
      {
        "type": "美食推荐",
        "description": "推荐当地特色美食和餐厅体验"
      },
      {
        "type": "住宿体验",
        "description": "分享特色酒店或民宿入住感受"
      },
      {
        "type": "摄影作品",
        "description": "展示旅途中的精彩瞬间和拍摄技巧"
      },
      {
        "type": "旅行故事",
        "description": "讲述旅途中的有趣故事和感悟"
      }
    ],
    "requirements": [
      "文章字数不少于1500字",
      "配图不少于10张，高清无水印",
      "内容原创，禁止抄袭",
      "信息准确，更新及时",
      "符合国家旅游政策规定"
    ],
    "rewards": [
      "优质稿件可获得200-1000元稿费",
      "获赠年度杂志会员资格",
      "优先参与平台各类活动",
      "优秀作者可签约成为专栏作家"
    ]
  }
}
